flet_router/__init__.py
flet_router/router.py
flet_router-1.0.0.dist-info/METADATA
flet_router-1.0.0.dist-info/WHEEL
flet_router-1.0.0.dist-info/licenses/LICENSE
flet_router-1.0.0.dist-info/RECORD
