Metadata-Version: 2.3
Name: flet-router
Version: 1.0.0
Summary: flet router
Project-URL: Homepage, https://github.com/taogya/flet_router
Project-URL: Bug Tracker, https://github.com/taogya/flet_router/issues
Author-email: Taogya <taogya.sfh@gmail.com>
License: BSD 3-Clause License
License-File: LICENSE
Classifier: License :: OSI Approved :: BSD License
Classifier: Programming Language :: Python :: 3
Requires-Python: >=3.8
Requires-Dist: flet>=0.23.0
